{
    "Players": {
        "Player": [
            {
                "_captain": "0",
                "_keeper": "0",
                "_matches": "2",
                "_player_first_name": "Christopher",
                "_player_id": "3636",
                "_player_initials": "C.J.L.",
                "_player_known_name": "Chris Rogers",
                "_player_last_name": "Rogers",
                "_team_id": "1",
                "_team_name": "Australia",
                "_twelthman": "0"
            },
            {
                "_captain": "0",
                "_keeper": "0",
                "_matches": "2",
                "_player_first_name": "Ryan",
                "_player_id": "4276",
                "_player_initials": "R.J.",
                "_player_known_name": "Ryan Harris",
                "_player_last_name": "Harris",
                "_team_id": "1",
                "_team_name": "Australia",
                "_twelthman": "0"
            },
            {
                "_captain": "0",
                "_keeper": "0",
                "_matches": "1",
                "_player_first_name": "Benjamin",
                "_player_id": "4489",
                "_player_initials": "B.A.",
                "_player_known_name": "Ben Stokes",
                "_player_last_name": "Stokes",
                "_team_id": "2",
                "_team_name": "England",
                "_twelthman": "0"
            },
            {
                "_captain": "0",
                "_keeper": "0",
                "_matches": "2",
                "_player_first_name": "Kevin",
                "_player_id": "3238",
                "_player_initials": "K.P.",
                "_player_known_name": "Kevin Pietersen",
                "_player_last_name": "Pietersen",
                "_team_id": "2",
                "_team_name": "England",
                "_twelthman": "0"
            },
            {
                "_captain": "0",
                "_keeper": "0",
                "_matches": "2",
                "_player_first_name": "Peter",
                "_player_id": "4242",
                "_player_initials": "P.M.",
                "_player_known_name": "Peter Siddle",
                "_player_last_name": "Siddle",
                "_team_id": "1",
                "_team_name": "Australia",
                "_twelthman": "0"
            },
            {
                "_captain": "-1",
                "_keeper": "0",
                "_matches": "2",
                "_player_first_name": "Alastair",
                "_player_id": "3297",
                "_player_initials": "A.N.",
                "_player_known_name": "Alastair Cook",
                "_player_last_name": "Cook",
                "_team_id": "2",
                "_team_name": "England",
                "_twelthman": "0"
            },
            {
                "_captain": "0",
                "_keeper": "0",
                "_matches": "2",
                "_player_first_name": "Ian",
                "_player_id": "3207",
                "_player_initials": "I.R.",
                "_player_known_name": "Ian Bell",
                "_player_last_name": "Bell",
                "_team_id": "2",
                "_team_name": "England",
                "_twelthman": "0"
            },
            {
                "_captain": "0",
                "_keeper": "0",
                "_matches": "2",
                "_player_first_name": "George",
                "_player_id": "4390",
                "_player_initials": "G.J.",
                "_player_known_name": "George Bailey",
                "_player_last_name": "Bailey",
                "_team_id": "1",
                "_team_name": "Australia",
                "_twelthman": "0"
            },
            {
                "_captain": "0",
                "_keeper": "0",
                "_matches": "2",
                "_player_first_name": "Mitchell",
                "_player_id": "3334",
                "_player_initials": "M.G.",
                "_player_known_name": "Mitchell Johnson",
                "_player_last_name": "Johnson",
                "_team_id": "1",
                "_team_name": "Australia",
                "_twelthman": "0"
            },
            {
                "_captain": "0",
                "_keeper": "0",
                "_matches": "2",
                "_player_first_name": "Steven",
                "_player_id": "4552",
                "_player_initials": "S.P.D.",
                "_player_known_name": "Steven Smith",
                "_player_last_name": "Smith",
                "_team_id": "1",
                "_team_name": "Australia",
                "_twelthman": "0"
            },
            {
                "_captain": "0",
                "_keeper": "0",
                "_matches": "1",
                "_player_first_name": "Mudhsuden",
                "_player_id": "3298",
                "_player_initials": "M.S.",
                "_player_known_name": "Monty Panesar",
                "_player_last_name": "Panesar",
                "_team_id": "2",
                "_team_name": "England",
                "_twelthman": "0"
            },
            {
                "_captain": "0",
                "_keeper": "0",
                "_matches": "2",
                "_player_first_name": "Joseph",
                "_player_id": "4541",
                "_player_initials": "J.E.",
                "_player_known_name": "Joe Root",
                "_player_last_name": "Root",
                "_team_id": "2",
                "_team_name": "England",
                "_twelthman": "0"
            },
            {
                "_captain": "0",
                "_keeper": "0",
                "_matches": "2",
                "_player_first_name": "Michael",
                "_player_id": "3576",
                "_player_initials": "M.A.",
                "_player_known_name": "Michael Carberry",
                "_player_last_name": "Carberry",
                "_team_id": "2",
                "_team_name": "England",
                "_twelthman": "0"
            },
            {
                "_captain": "0",
                "_keeper": "0",
                "_matches": "1",
                "_player_first_name": "Christopher",
                "_player_id": "3282",
                "_player_initials": "C.T.",
                "_player_known_name": "Chris Tremlett",
                "_player_last_name": "Tremlett",
                "_team_id": "2",
                "_team_name": "England",
                "_twelthman": "0"
            },
            {
                "_captain": "0",
                "_keeper": "0",
                "_matches": "2",
                "_player_first_name": "James",
                "_player_id": "3065",
                "_player_initials": "J.M.",
                "_player_known_name": "James Anderson",
                "_player_last_name": "Anderson",
                "_team_id": "2",
                "_team_name": "England",
                "_twelthman": "0"
            },
            {
                "_captain": "0",
                "_keeper": "0",
                "_matches": "1",
                "_player_first_name": "Ian",
                "_player_id": "3542",
                "_player_initials": "I.J.L.",
                "_player_known_name": "Jonathan Trott",
                "_player_last_name": "Trott",
                "_team_id": "2",
                "_team_name": "England",
                "_twelthman": "0"
            },
            {
                "_captain": "0",
                "_keeper": "0",
                "_matches": "2",
                "_player_first_name": "Graeme",
                "_player_id": "2906",
                "_player_initials": "G.P.",
                "_player_known_name": "Graeme Swann",
                "_player_last_name": "Swann",
                "_team_id": "2",
                "_team_name": "England",
                "_twelthman": "0"
            },
            {
                "_captain": "0",
                "_keeper": "-1",
                "_matches": "2",
                "_player_first_name": "Matthew",
                "_player_id": "3239",
                "_player_initials": "M.J.",
                "_player_known_name": "Matt Prior",
                "_player_last_name": "Prior",
                "_team_id": "2",
                "_team_name": "England",
                "_twelthman": "0"
            },
            {
                "_captain": "0",
                "_keeper": "-1",
                "_matches": "2",
                "_player_first_name": "Bradley",
                "_player_id": "2707",
                "_player_initials": "B.J.",
                "_player_known_name": "Brad Haddin",
                "_player_last_name": "Haddin",
                "_team_id": "1",
                "_team_name": "Australia",
                "_twelthman": "0"
            },
            {
                "_captain": "0",
                "_keeper": "0",
                "_matches": "2",
                "_player_first_name": "Nathan",
                "_player_id": "5144",
                "_player_initials": "N.M.",
                "_player_known_name": "Nathan Lyon",
                "_player_last_name": "Lyon",
                "_team_id": "1",
                "_team_name": "Australia",
                "_twelthman": "0"
            },
            {
                "_captain": "0",
                "_keeper": "0",
                "_matches": "2",
                "_player_first_name": "David",
                "_player_id": "4275",
                "_player_initials": "D.A.",
                "_player_known_name": "David Warner",
                "_player_last_name": "Warner",
                "_team_id": "1",
                "_team_name": "Australia",
                "_twelthman": "0"
            },
            {
                "_captain": "0",
                "_keeper": "0",
                "_matches": "2",
                "_player_first_name": "Shane",
                "_player_id": "3017",
                "_player_initials": "S.R.",
                "_player_known_name": "Shane Watson",
                "_player_last_name": "Watson",
                "_team_id": "1",
                "_team_name": "Australia",
                "_twelthman": "0"
            },
            {
                "_captain": "0",
                "_keeper": "0",
                "_matches": "2",
                "_player_first_name": "Stuart",
                "_player_id": "3425",
                "_player_initials": "S.C.J.",
                "_player_known_name": "Stuart Broad",
                "_player_last_name": "Broad",
                "_team_id": "2",
                "_team_name": "England",
                "_twelthman": "0"
            },
            {
                "_captain": "-1",
                "_keeper": "0",
                "_matches": "2",
                "_player_first_name": "Michael",
                "_player_id": "3067",
                "_player_initials": "M.J.",
                "_player_known_name": "Michael Clarke",
                "_player_last_name": "Clarke",
                "_team_id": "1",
                "_team_name": "Australia",
                "_twelthman": "0"
            }
        ]
    },
    "Ranking": [
        {
            "Player": [
                {
                    "_id": "4275",
                    "_balls_faced": "385",
                    "_runs_scored": "285"
                },
                {
                    "_id": "3067",
                    "_balls_faced": "436",
                    "_runs_scored": "284"
                },
                {
                    "_id": "2707",
                    "_balls_faced": "385",
                    "_runs_scored": "265"
                },
                {
                    "_id": "4541",
                    "_balls_faced": "367",
                    "_runs_scored": "130"
                },
                {
                    "_id": "3207",
                    "_balls_faced": "211",
                    "_runs_scored": "115"
                },
                {
                    "_id": "3576",
                    "_balls_faced": "310",
                    "_runs_scored": "114"
                },
                {
                    "_id": "3334",
                    "_balls_faced": "192",
                    "_runs_scored": "108"
                },
                {
                    "_id": "3238",
                    "_balls_faced": "205",
                    "_runs_scored": "101"
                },
                {
                    "_id": "3636",
                    "_balls_faced": "267",
                    "_runs_scored": "91"
                },
                {
                    "_id": "4390",
                    "_balls_faced": "168",
                    "_runs_scored": "90"
                },
                {
                    "_id": "3297",
                    "_balls_faced": "243",
                    "_runs_scored": "82"
                },
                {
                    "_id": "3017",
                    "_balls_faced": "219",
                    "_runs_scored": "79"
                },
                {
                    "_id": "3239",
                    "_balls_faced": "115",
                    "_runs_scored": "73"
                },
                {
                    "_id": "3425",
                    "_balls_faced": "75",
                    "_runs_scored": "65"
                },
                {
                    "_id": "4276",
                    "_balls_faced": "71",
                    "_runs_scored": "64"
                },
                {
                    "_id": "4552",
                    "_balls_faced": "137",
                    "_runs_scored": "60"
                },
                {
                    "_id": "4489",
                    "_balls_faced": "102",
                    "_runs_scored": "29"
                },
                {
                    "_id": "3542",
                    "_balls_faced": "28",
                    "_runs_scored": "19"
                },
                {
                    "_id": "5144",
                    "_balls_faced": "42",
                    "_runs_scored": "18"
                },
                {
                    "_id": "3065",
                    "_balls_faced": "33",
                    "_runs_scored": "17"
                },
                {
                    "_id": "3282",
                    "_balls_faced": "68",
                    "_runs_scored": "15"
                },
                {
                    "_id": "2906",
                    "_balls_faced": "28",
                    "_runs_scored": "13"
                },
                {
                    "_id": "4242",
                    "_balls_faced": "32",
                    "_runs_scored": "13"
                },
                {
                    "_id": "3298",
                    "_balls_faced": "42",
                    "_runs_scored": "2"
                }
            ],
            "_name": "Player Top Scorer"
        },
        {
            "Player": [
                {
                    "_id": "4276",
                    "_strike_rate": "90.14"
                },
                {
                    "_id": "3425",
                    "_strike_rate": "86.67"
                },
                {
                    "_id": "4275",
                    "_strike_rate": "74.03"
                },
                {
                    "_id": "2707",
                    "_strike_rate": "68.83"
                },
                {
                    "_id": "3067",
                    "_strike_rate": "65.14"
                },
                {
                    "_id": "3239",
                    "_strike_rate": "63.48"
                },
                {
                    "_id": "3334",
                    "_strike_rate": "56.25"
                },
                {
                    "_id": "3207",
                    "_strike_rate": "54.50"
                },
                {
                    "_id": "4390",
                    "_strike_rate": "53.57"
                },
                {
                    "_id": "3238",
                    "_strike_rate": "49.27"
                },
                {
                    "_id": "4552",
                    "_strike_rate": "43.80"
                },
                {
                    "_id": "5144",
                    "_strike_rate": "42.86"
                },
                {
                    "_id": "3576",
                    "_strike_rate": "36.77"
                },
                {
                    "_id": "3017",
                    "_strike_rate": "36.07"
                },
                {
                    "_id": "4541",
                    "_strike_rate": "35.42"
                },
                {
                    "_id": "3636",
                    "_strike_rate": "34.08"
                },
                {
                    "_id": "3297",
                    "_strike_rate": "33.74"
                },
                {
                    "_id": "4489",
                    "_strike_rate": "28.43"
                },
                {
                    "_id": "3282",
                    "_strike_rate": "22.06"
                },
                {
                    "_id": "3298",
                    "_strike_rate": "4.76"
                }
            ],
            "_name": "Player Fastest Scorer"
        },
        {
            "Player": [
                {
                    "_id": "4275",
                    "_fours_scored": "32"
                },
                {
                    "_id": "3067",
                    "_fours_scored": "28"
                },
                {
                    "_id": "2707",
                    "_fours_scored": "24"
                },
                {
                    "_id": "3576",
                    "_fours_scored": "16"
                },
                {
                    "_id": "4541",
                    "_fours_scored": "14"
                },
                {
                    "_id": "3239",
                    "_fours_scored": "13"
                },
                {
                    "_id": "3207",
                    "_fours_scored": "13"
                },
                {
                    "_id": "3636",
                    "_fours_scored": "12"
                },
                {
                    "_id": "3334",
                    "_fours_scored": "11"
                },
                {
                    "_id": "3017",
                    "_fours_scored": "9"
                },
                {
                    "_id": "3425",
                    "_fours_scored": "7"
                },
                {
                    "_id": "4552",
                    "_fours_scored": "7"
                },
                {
                    "_id": "4276",
                    "_fours_scored": "6"
                },
                {
                    "_id": "4489",
                    "_fours_scored": "5"
                },
                {
                    "_id": "4390",
                    "_fours_scored": "5"
                },
                {
                    "_id": "3238",
                    "_fours_scored": "5"
                },
                {
                    "_id": "3297",
                    "_fours_scored": "5"
                },
                {
                    "_id": "3542",
                    "_fours_scored": "2"
                },
                {
                    "_id": "4242",
                    "_fours_scored": "2"
                },
                {
                    "_id": "3065",
                    "_fours_scored": "2"
                },
                {
                    "_id": "3282",
                    "_fours_scored": "2"
                },
                {
                    "_id": "5144",
                    "_fours_scored": "1"
                }
            ],
            "_name": "Player Fours Scored"
        },
        {
            "Player": [
                {
                    "_id": "2707",
                    "_sixes_scored": "6"
                },
                {
                    "_id": "4390",
                    "_sixes_scored": "5"
                },
                {
                    "_id": "3207",
                    "_sixes_scored": "4"
                },
                {
                    "_id": "3334",
                    "_sixes_scored": "3"
                },
                {
                    "_id": "3238",
                    "_sixes_scored": "3"
                },
                {
                    "_id": "4276",
                    "_sixes_scored": "2"
                },
                {
                    "_id": "4275",
                    "_sixes_scored": "2"
                },
                {
                    "_id": "5144",
                    "_sixes_scored": "1"
                },
                {
                    "_id": "3425",
                    "_sixes_scored": "1"
                },
                {
                    "_id": "3017",
                    "_sixes_scored": "1"
                },
                {
                    "_id": "3067",
                    "_sixes_scored": "1"
                }
            ],
            "_name": "Player Sixes Scored"
        },
        {
            "Player": [
                {
                    "_id": "3334",
                    "_bowling_average": "12.71",
                    "_wickets_taken": "17"
                },
                {
                    "_id": "3425",
                    "_bowling_average": "23.00",
                    "_wickets_taken": "11"
                },
                {
                    "_id": "4276",
                    "_bowling_average": "20.25",
                    "_wickets_taken": "8"
                },
                {
                    "_id": "4242",
                    "_bowling_average": "20.00",
                    "_wickets_taken": "7"
                },
                {
                    "_id": "5144",
                    "_bowling_average": "34.17",
                    "_wickets_taken": "6"
                },
                {
                    "_id": "3065",
                    "_bowling_average": "48.80",
                    "_wickets_taken": "5"
                },
                {
                    "_id": "2906",
                    "_bowling_average": "99.25",
                    "_wickets_taken": "4"
                },
                {
                    "_id": "3282",
                    "_bowling_average": "30.00",
                    "_wickets_taken": "4"
                },
                {
                    "_id": "3298",
                    "_bowling_average": "99.00",
                    "_wickets_taken": "2"
                },
                {
                    "_id": "4489",
                    "_bowling_average": "45.00",
                    "_wickets_taken": "2"
                },
                {
                    "_id": "4552",
                    "_bowling_average": "58.00",
                    "_wickets_taken": "1"
                },
                {
                    "_id": "3017",
                    "_bowling_average": "6.00",
                    "_wickets_taken": "1"
                }
            ],
            "_name": "Player Wickets Taken"
        },
        {
            "Player": [
                {
                    "_id": "4552",
                    "_bowling_econ": "5.27",
                    "_overs_bowled": "11"
                },
                {
                    "_id": "2906",
                    "_bowling_econ": "4.05",
                    "_overs_bowled": "98"
                },
                {
                    "_id": "3298",
                    "_bowling_econ": "3.67",
                    "_overs_bowled": "54"
                },
                {
                    "_id": "4489",
                    "_bowling_econ": "3.60",
                    "_overs_bowled": "25"
                },
                {
                    "_id": "4541",
                    "_bowling_econ": "3.44",
                    "_overs_bowled": "18"
                },
                {
                    "_id": "3282",
                    "_bowling_econ": "3.33",
                    "_overs_bowled": "36"
                },
                {
                    "_id": "3425",
                    "_bowling_econ": "3.33",
                    "_overs_bowled": "76"
                },
                {
                    "_id": "3065",
                    "_bowling_econ": "3.01",
                    "_overs_bowled": "81"
                },
                {
                    "_id": "5144",
                    "_bowling_econ": "2.73",
                    "_overs_bowled": "75"
                },
                {
                    "_id": "3334",
                    "_bowling_econ": "2.72",
                    "_overs_bowled": "79"
                },
                {
                    "_id": "4276",
                    "_bowling_econ": "2.39",
                    "_overs_bowled": "67"
                },
                {
                    "_id": "4242",
                    "_bowling_econ": "2.35",
                    "_overs_bowled": "59"
                },
                {
                    "_id": "3017",
                    "_bowling_econ": "0.55",
                    "_overs_bowled": "11"
                }
            ],
            "_name": "Player Worst Bowling Economy"
        },
        {
            "Player": [
                {
                    "_id": "3017",
                    "_bowling_econ": "0.55",
                    "_overs_bowled": "11"
                },
                {
                    "_id": "4242",
                    "_bowling_econ": "2.35",
                    "_overs_bowled": "59"
                },
                {
                    "_id": "4276",
                    "_bowling_econ": "2.39",
                    "_overs_bowled": "67"
                },
                {
                    "_id": "3334",
                    "_bowling_econ": "2.72",
                    "_overs_bowled": "79"
                },
                {
                    "_id": "5144",
                    "_bowling_econ": "2.73",
                    "_overs_bowled": "75"
                },
                {
                    "_id": "3065",
                    "_bowling_econ": "3.01",
                    "_overs_bowled": "81"
                },
                {
                    "_id": "3282",
                    "_bowling_econ": "3.33",
                    "_overs_bowled": "36"
                },
                {
                    "_id": "3425",
                    "_bowling_econ": "3.33",
                    "_overs_bowled": "76"
                },
                {
                    "_id": "4541",
                    "_bowling_econ": "3.44",
                    "_overs_bowled": "18"
                },
                {
                    "_id": "4489",
                    "_bowling_econ": "3.60",
                    "_overs_bowled": "25"
                },
                {
                    "_id": "3298",
                    "_bowling_econ": "3.67",
                    "_overs_bowled": "54"
                },
                {
                    "_id": "2906",
                    "_bowling_econ": "4.05",
                    "_overs_bowled": "98"
                },
                {
                    "_id": "4552",
                    "_bowling_econ": "5.27",
                    "_overs_bowled": "11"
                }
            ],
            "_name": "Player Best Bowling Economy"
        },
        {
            "Player": [
                {
                    "_id": "3239",
                    "_dismissals_as_keeper": "7"
                },
                {
                    "_id": "2707",
                    "_dismissals_as_keeper": "7"
                }
            ],
            "_name": "Player Dismissals As WicketKeeper"
        },
        {
            "Player": [
                {
                    "_id": "3067",
                    "_leg_side_runs": "171"
                },
                {
                    "_id": "2707",
                    "_leg_side_runs": "170"
                },
                {
                    "_id": "4275",
                    "_leg_side_runs": "107"
                },
                {
                    "_id": "4541",
                    "_leg_side_runs": "73"
                },
                {
                    "_id": "3334",
                    "_leg_side_runs": "71"
                },
                {
                    "_id": "3238",
                    "_leg_side_runs": "65"
                },
                {
                    "_id": "4390",
                    "_leg_side_runs": "64"
                },
                {
                    "_id": "3576",
                    "_leg_side_runs": "57"
                },
                {
                    "_id": "3207",
                    "_leg_side_runs": "47"
                },
                {
                    "_id": "3239",
                    "_leg_side_runs": "44"
                },
                {
                    "_id": "4276",
                    "_leg_side_runs": "37"
                },
                {
                    "_id": "4552",
                    "_leg_side_runs": "37"
                },
                {
                    "_id": "3017",
                    "_leg_side_runs": "37"
                },
                {
                    "_id": "3297",
                    "_leg_side_runs": "37"
                },
                {
                    "_id": "3425",
                    "_leg_side_runs": "33"
                },
                {
                    "_id": "3636",
                    "_leg_side_runs": "22"
                },
                {
                    "_id": "3542",
                    "_leg_side_runs": "19"
                },
                {
                    "_id": "4489",
                    "_leg_side_runs": "16"
                },
                {
                    "_id": "5144",
                    "_leg_side_runs": "15"
                },
                {
                    "_id": "3065",
                    "_leg_side_runs": "12"
                },
                {
                    "_id": "4242",
                    "_leg_side_runs": "11"
                },
                {
                    "_id": "3282",
                    "_leg_side_runs": "9"
                },
                {
                    "_id": "2906",
                    "_leg_side_runs": "6"
                }
            ],
            "_name": "Player Leg Side Runs"
        },
        {
            "Player": [
                {
                    "_id": "4275",
                    "_off_side_runs": "178"
                },
                {
                    "_id": "3067",
                    "_off_side_runs": "113"
                },
                {
                    "_id": "2707",
                    "_off_side_runs": "95"
                },
                {
                    "_id": "3636",
                    "_off_side_runs": "69"
                },
                {
                    "_id": "3207",
                    "_off_side_runs": "68"
                },
                {
                    "_id": "3576",
                    "_off_side_runs": "57"
                },
                {
                    "_id": "4541",
                    "_off_side_runs": "57"
                },
                {
                    "_id": "3297",
                    "_off_side_runs": "45"
                },
                {
                    "_id": "3017",
                    "_off_side_runs": "42"
                },
                {
                    "_id": "3334",
                    "_off_side_runs": "37"
                },
                {
                    "_id": "3238",
                    "_off_side_runs": "36"
                },
                {
                    "_id": "3425",
                    "_off_side_runs": "32"
                },
                {
                    "_id": "3239",
                    "_off_side_runs": "29"
                },
                {
                    "_id": "4276",
                    "_off_side_runs": "27"
                },
                {
                    "_id": "4390",
                    "_off_side_runs": "26"
                },
                {
                    "_id": "4552",
                    "_off_side_runs": "23"
                },
                {
                    "_id": "4489",
                    "_off_side_runs": "13"
                },
                {
                    "_id": "2906",
                    "_off_side_runs": "7"
                },
                {
                    "_id": "3282",
                    "_off_side_runs": "6"
                },
                {
                    "_id": "3065",
                    "_off_side_runs": "5"
                },
                {
                    "_id": "5144",
                    "_off_side_runs": "3"
                },
                {
                    "_id": "4242",
                    "_off_side_runs": "2"
                },
                {
                    "_id": "3298",
                    "_off_side_runs": "2"
                }
            ],
            "_name": "Player Off Side Runs"
        },
        {
            "Team": [
                {
                    "_id": "1",
                    "_runs_scored": "1398"
                },
                {
                    "_id": "2",
                    "_runs_scored": "799"
                }
            ],
            "_name": "Team Runs Scored"
        },
        {
            "Team": [
                {
                    "_id": "2",
                    "_catches": "33"
                },
                {
                    "_id": "1",
                    "_catches": "23"
                }
            ],
            "_name": "Team Catches"
        },
        {
            "Team": [
                {
                    "_id": "2",
                    "_dropped_catches": "5"
                },
                {
                    "_id": "1",
                    "_dropped_catches": "4"
                }
            ],
            "_name": "Team Dropped Catches"
        },
        {
            "Team": [
                {
                    "_id": "1",
                    "_boundaries": "158",
                    "_fours_scored": "137",
                    "_sixes_scored": "21"
                },
                {
                    "_id": "2",
                    "_boundaries": "92",
                    "_fours_scored": "84",
                    "_sixes_scored": "8"
                }
            ],
            "_name": "Team Boundaries"
        },
        {
            "Team": [
                {
                    "_id": "1",
                    "_lbw_decisions": "1"
                },
                {
                    "_id": "2",
                    "_lbw_decisions": "0"
                }
            ],
            "_name": "Team LBW Decisions"
        },
        {
            "Partnership": [
                {
                    "_batsman_1": "3636",
                    "_batsman_2": "4275",
                    "_game_id": "35062",
                    "_innings_id": "3",
                    "_over_ball": "23.1",
                    "_runs": "67"
                },
                {
                    "_batsman_1": "3636",
                    "_batsman_2": "4275",
                    "_game_id": "35063",
                    "_innings_id": "1",
                    "_over_ball": "7.6",
                    "_runs": "34"
                },
                {
                    "_batsman_1": "3297",
                    "_batsman_2": "3576",
                    "_game_id": "35062",
                    "_innings_id": "2",
                    "_over_ball": "10.2",
                    "_runs": "28"
                },
                {
                    "_batsman_1": "3636",
                    "_batsman_2": "4275",
                    "_game_id": "35062",
                    "_innings_id": "1",
                    "_over_ball": "3.1",
                    "_runs": "12"
                },
                {
                    "_batsman_1": "3297",
                    "_batsman_2": "3576",
                    "_game_id": "35063",
                    "_innings_id": "2",
                    "_over_ball": "2.4",
                    "_runs": "9"
                },
                {
                    "_batsman_1": "3636",
                    "_batsman_2": "4275",
                    "_game_id": "35063",
                    "_innings_id": "3",
                    "_over_ball": "2.2",
                    "_runs": "4"
                },
                {
                    "_batsman_1": "3297",
                    "_batsman_2": "3576",
                    "_game_id": "35062",
                    "_innings_id": "4",
                    "_over_ball": "4.4",
                    "_runs": "1"
                },
                {
                    "_batsman_1": "3297",
                    "_batsman_2": "3576",
                    "_game_id": "35063",
                    "_innings_id": "4",
                    "_over_ball": "1.3",
                    "_runs": "1"
                }
            ],
            "_name": "Highest Opening Partnerships"
        }
    ],
    "Teams": {
        "Team": [
            {
                "_id": "1",
                "_matches": "2",
                "_name": "Australia"
            },
            {
                "_id": "2",
                "_matches": "2",
                "_name": "England"
            }
        ]
    }
}